<?xml version="1.0"?>
<!--<!DOCTYPE metadata SYSTEM "http://www.esri.com/metadata/esriprof80.dtd">-->
<metadata xml:lang="en"><Esri><CreaDate>20100424</CreaDate><CreaTime>10385200</CreaTime><SyncOnce>TRUE</SyncOnce><MetaID>{095BC4C4-21E8-4556-97F2-4C37BCA80485}</MetaID></Esri><idinfo><citation><citeinfo><onlink Sync="TRUE">\\Iserver\GIS_LIBRARY\VOTING_BACKUP\Data\precinct11</onlink></citeinfo></citation></idinfo><distInfo><distributor><distorTran><onLineSrc><linkage Sync="TRUE">file://\\Iserver\GIS_LIBRARY\VOTING_BACKUP\Data\precinct11</linkage><protocol Sync="TRUE">Local Area Network</protocol></onLineSrc></distorTran></distributor></distInfo><dataqual><lineage><procstep><procdesc Sync="TRUE">Dataset copied.</procdesc><srcused Sync="TRUE">Z:\Data\precinct11</srcused><procdate Sync="TRUE">20100424</procdate><proctime Sync="TRUE">10385200</proctime></procstep></lineage></dataqual></metadata>
